{"699130426337263616": {"startgame": {"Enabled": true, "Cooldown": 0, "WhitelistEnabled": false, "Whitelist": null, "BlacklistEnabled": true, "Blacklist": null}, "endgame": {"Enabled": true, "Cooldown": 0, "WhitelistEnabled": true, "Whitelist": null, "BlacklistEnabled": false, "Blacklist": null}, "joingame": {"Enabled": true, "Cooldown": 0, "WhitelistEnabled": false, "Whitelist": null, "BlacklistEnabled": true, "Blacklist": null}, "leavegame": {"Enabled": true, "Cooldown": 0, "WhitelistEnabled": false, "Whitelist": null, "BlacklistEnabled": true, "Blacklist": null}, "kick": {"Enabled": true, "Cooldown": 0, "WhitelistEnabled": true, "Whitelist": null, "BlacklistEnabled": false, "Blacklist": null}, "spectate": {"Enabled": true, "Cooldown": 0, "WhitelistEnabled": false, "Whitelist": null, "BlacklistEnabled": true, "Blacklist": null}, "stats": {"Enabled": true, "Cooldown": 0, "WhitelistEnabled": false, "Whitelist": null, "BlacklistEnabled": true, "Blacklist": null}, "globalstats": {"Enabled": true, "Cooldown": 0, "WhitelistEnabled": false, "Whitelist": null, "BlacklistEnabled": true, "Blacklist": null}, "leaderboard": {"Enabled": true, "Cooldown": 0, "WhitelistEnabled": false, "Whitelist": null, "BlacklistEnabled": true, "Blacklist": null}, "globalleaderboard": {"Enabled": true, "Cooldown": 0, "WhitelistEnabled": false, "Whitelist": null, "BlacklistEnabled": true, "Blacklist": null}, "allowalerts": {"Enabled": true, "Cooldown": 0, "WhitelistEnabled": false, "Whitelist": null, "BlacklistEnabled": true, "Blacklist": null}, "settings": {"Enabled": true, "Cooldown": 0, "WhitelistEnabled": true, "Whitelist": null, "BlacklistEnabled": false, "Blacklist": null}}, "846954928941432862": {"startgame": {"Enabled": true, "Cooldown": 0, "WhitelistEnabled": false, "Whitelist": null, "BlacklistEnabled": true, "Blacklist": null}, "endgame": {"Enabled": true, "Cooldown": 0, "WhitelistEnabled": true, "Whitelist": null, "BlacklistEnabled": false, "Blacklist": null}, "joingame": {"Enabled": true, "Cooldown": 0, "WhitelistEnabled": false, "Whitelist": null, "BlacklistEnabled": true, "Blacklist": null}, "leavegame": {"Enabled": true, "Cooldown": 0, "WhitelistEnabled": false, "Whitelist": null, "BlacklistEnabled": true, "Blacklist": null}, "kick": {"Enabled": true, "Cooldown": 0, "WhitelistEnabled": true, "Whitelist": null, "BlacklistEnabled": false, "Blacklist": null}, "spectate": {"Enabled": true, "Cooldown": 0, "WhitelistEnabled": false, "Whitelist": null, "BlacklistEnabled": true, "Blacklist": null}, "stats": {"Enabled": true, "Cooldown": 0, "WhitelistEnabled": false, "Whitelist": null, "BlacklistEnabled": true, "Blacklist": null}, "globalstats": {"Enabled": true, "Cooldown": 0, "WhitelistEnabled": false, "Whitelist": null, "BlacklistEnabled": true, "Blacklist": null}, "leaderboard": {"Enabled": true, "Cooldown": 0, "WhitelistEnabled": false, "Whitelist": null, "BlacklistEnabled": true, "Blacklist": null}, "globalleaderboard": {"Enabled": true, "Cooldown": 0, "WhitelistEnabled": false, "Whitelist": null, "BlacklistEnabled": true, "Blacklist": null}, "allowalerts": {"Enabled": true, "Cooldown": 0, "WhitelistEnabled": false, "Whitelist": null, "BlacklistEnabled": true, "Blacklist": null}, "settings": {"Enabled": true, "Cooldown": 0, "WhitelistEnabled": true, "Whitelist": null, "BlacklistEnabled": false, "Blacklist": null}}, "847483414395355166": {"startgame": {"Enabled": true, "Cooldown": 0, "WhitelistEnabled": false, "Whitelist": null, "BlacklistEnabled": true, "Blacklist": null}, "endgame": {"Enabled": true, "Cooldown": 0, "WhitelistEnabled": true, "Whitelist": null, "BlacklistEnabled": false, "Blacklist": null}, "joingame": {"Enabled": true, "Cooldown": 0, "WhitelistEnabled": false, "Whitelist": null, "BlacklistEnabled": true, "Blacklist": null}, "leavegame": {"Enabled": true, "Cooldown": 0, "WhitelistEnabled": false, "Whitelist": null, "BlacklistEnabled": true, "Blacklist": null}, "kick": {"Enabled": true, "Cooldown": 0, "WhitelistEnabled": true, "Whitelist": null, "BlacklistEnabled": false, "Blacklist": null}, "spectate": {"Enabled": true, "Cooldown": 0, "WhitelistEnabled": false, "Whitelist": null, "BlacklistEnabled": true, "Blacklist": null}, "stats": {"Enabled": true, "Cooldown": 0, "WhitelistEnabled": false, "Whitelist": null, "BlacklistEnabled": true, "Blacklist": null}, "globalstats": {"Enabled": true, "Cooldown": 0, "WhitelistEnabled": false, "Whitelist": null, "BlacklistEnabled": true, "Blacklist": null}, "leaderboard": {"Enabled": true, "Cooldown": 0, "WhitelistEnabled": false, "Whitelist": null, "BlacklistEnabled": true, "Blacklist": null}, "globalleaderboard": {"Enabled": true, "Cooldown": 0, "WhitelistEnabled": false, "Whitelist": null, "BlacklistEnabled": true, "Blacklist": null}, "allowalerts": {"Enabled": true, "Cooldown": 0, "WhitelistEnabled": false, "Whitelist": null, "BlacklistEnabled": true, "Blacklist": null}, "settings": {"Enabled": true, "Cooldown": 0, "WhitelistEnabled": true, "Whitelist": null, "BlacklistEnabled": false, "Blacklist": null}}}